{
  "title": "Proyectos GeneSIG Solutions",
  "description": "Somos una organización que brinda soluciones integrales especializadas en el campo de la geomatica e informatica a particulares, instacias publicas y privadas. Asi mismo promueve la importancia de la Geomatica para el desarrollo integral del territorio, una organizacion que al mismo tiempo, es un espacio para el crecimiento profesional de las afinidades geográficas e infomaticas del equipo y del mercado actual. Nuestra vision es convertirnos en una referencia Venezolana para la comunidad nacional e internacional, estableciendo nuevas formas de encuentro y de trabajo en este ámplio campo",
  "links": [
    { "id": "0", "titulo": "Sitio Oficial",  "pagina": "http://geoportal.lachuleta.info/", 
      "imagen":"https://github.com/eduardoeguillen/genesigapp/blob/master/images/giscity.png" },
    { "id": "1", "titulo": "Sitio Oficial",  "pagina": "http://t.me/sigvenezuela" },
    { "id": "4", "titulo": "Geoportal",  "pagina": "http://geoportal.lachuleta.info/" },
    { "id": "8", "titulo": "Instagram",  "pagina": "https://www.instagram.com/eduguillenc" },
    { "id": "9", "titulo": "Facebook",  "pagina": "https://www.facebook.com/" },
    { "id": "10", "titulo": "Twitter",  "pagina": "https://twitter.com/eduguillenc" },
    { "id": "11", "titulo": "Youtube",  "pagina": "https://www.youtube.com/" },
    { "id": "12", "titulo": "LinkedIn",  "pagina": "https://www.linkedin.com/" }
  ]
}

